<annotation>
	<folder>Tigre</folder>
	<filename>181.jpg</filename>
	<path>C:\Users\HP\Documents\Tigre\181.jpg</path>
	<source>
		<database>Unknown</database>
	</source>
	<size>
		<width>1500</width>
		<height>1266</height>
		<depth>3</depth>
	</size>
	<segmented>0</segmented>
	<object>
		<name>Tigre</name>
		<pose>Unspecified</pose>
		<truncated>0</truncated>
		<difficult>0</difficult>
		<bndbox>
			<xmin>62</xmin>
			<ymin>198</ymin>
			<xmax>1429</xmax>
			<ymax>977</ymax>
		</bndbox>
	</object>
</annotation>
