<annotation>
	<folder>images</folder>
	<filename>428.jpg</filename>
	<path>/home/yeshua/Escritorio/Deteccion2/images/428.jpg</path>
	<source>
		<database>Unknown</database>
	</source>
	<size>
		<width>840</width>
		<height>535</height>
		<depth>3</depth>
	</size>
	<segmented>0</segmented>
	<object>
		<name>Lobo</name>
		<pose>Unspecified</pose>
		<truncated>0</truncated>
		<difficult>0</difficult>
		<bndbox>
			<xmin>74</xmin>
			<ymin>23</ymin>
			<xmax>678</xmax>
			<ymax>512</ymax>
		</bndbox>
	</object>
</annotation>
