<annotation>
	<folder>Yoshi</folder>
	<filename>B21.jpg</filename>
	<path>/home/yeshua/Documentos/Yoshi/B21.jpg</path>
	<source>
		<database>Unknown</database>
	</source>
	<size>
		<width>576</width>
		<height>576</height>
		<depth>3</depth>
	</size>
	<segmented>0</segmented>
	<object>
		<name>Yoshi</name>
		<pose>Unspecified</pose>
		<truncated>1</truncated>
		<difficult>0</difficult>
		<bndbox>
			<xmin>147</xmin>
			<ymin>1</ymin>
			<xmax>506</xmax>
			<ymax>265</ymax>
		</bndbox>
	</object>
</annotation>
